[{"name":"undefined","children":[{"id":"101021","name":"undefined + 24"},{"id":"101022","name":"undefined + 30"},{"id":"101031","name":"undefined + 1.2%"},{"id":"101032","name":"undefined + 1.5%"},{"id":"101051","name":"undefined + 2"},{"id":"101052","name":"undefined + 2"},{"id":"101061","name":"undefined + 1.2%"},{"id":"101062","name":"undefined + 1.5%"},{"id":"101081","name":"undefined + 2"},{"id":"101082","name":"undefined + 2"},{"id":"101091","name":"undefined + 1.5%"},{"id":"101092","name":"undefined + 1.8%"},{"id":"101201","name":"undefined + 0.8%"},{"id":"101202","name":"undefined + 1.0%"},{"id":"101221","name":"undefined + 1.5%"},{"id":"101222","name":"undefined + 1.9%"},{"id":"101231","name":"undefined + 1.3%"},{"id":"101232","name":"undefined + 1.6%"},{"id":"101241","name":"undefined + 466.0%"},{"id":"101242","name":"undefined + 583.0%"},{"id":"201021","name":"undefined + 50"},{"id":"201022","name":"undefined + 61"},{"id":"201023","name":"undefined + 72"},{"id":"201031","name":"undefined + 1.6%"},{"id":"201032","name":"undefined + 2.0%"},{"id":"201033","name":"undefined + 2.3%"},{"id":"201051","name":"undefined + 3"},{"id":"201052","name":"undefined + 4"},{"id":"201053","name":"undefined + 5"},{"id":"201061","name":"undefined + 1.6%"},{"id":"201062","name":"undefined + 2.0%"},{"id":"201063","name":"undefined + 2.3%"},{"id":"201081","name":"undefined + 4"},{"id":"201082","name":"undefined + 5"},{"id":"201083","name":"undefined + 6"},{"id":"201091","name":"undefined + 2.0%"},{"id":"201092","name":"undefined + 2.5%"},{"id":"201093","name":"undefined + 2.9%"},{"id":"201201","name":"undefined + 1.1%"},{"id":"201202","name":"undefined + 1.3%"},{"id":"201203","name":"undefined + 1.5%"},{"id":"201221","name":"undefined + 2.2%"},{"id":"201222","name":"undefined + 2.6%"},{"id":"201223","name":"undefined + 3.1%"},{"id":"201231","name":"undefined + 1.8%"},{"id":"201232","name":"undefined + 2.2%"},{"id":"201233","name":"undefined + 2.6%"},{"id":"201241","name":"undefined + 653.0%"},{"id":"201242","name":"undefined + 793.0%"},{"id":"201243","name":"undefined + 933.0%"},{"id":"301021","name":"undefined + 100"},{"id":"301022","name":"undefined + 115"},{"id":"301023","name":"undefined + 129"},{"id":"301024","name":"undefined + 143"},{"id":"301031","name":"undefined + 2.5%"},{"id":"301032","name":"undefined + 2.8%"},{"id":"301033","name":"undefined + 3.2%"},{"id":"301034","name":"undefined + 3.5%"},{"id":"301051","name":"undefined + 7"},{"id":"301052","name":"undefined + 7"},{"id":"301053","name":"undefined + 8"},{"id":"301054","name":"undefined + 9"},{"id":"301061","name":"undefined + 2.5%"},{"id":"301062","name":"undefined + 2.8%"},{"id":"301063","name":"undefined + 3.2%"},{"id":"301064","name":"undefined + 3.5%"},{"id":"301081","name":"undefined + 8"},{"id":"301082","name":"undefined + 9"},{"id":"301083","name":"undefined + 10"},{"id":"301084","name":"undefined + 11"},{"id":"301091","name":"undefined + 3.1%"},{"id":"301092","name":"undefined + 3.5%"},{"id":"301093","name":"undefined + 3.9%"},{"id":"301094","name":"undefined + 4.4%"},{"id":"301201","name":"undefined + 1.6%"},{"id":"301202","name":"undefined + 1.9%"},{"id":"301203","name":"undefined + 2.1%"},{"id":"301204","name":"undefined + 2.3%"},{"id":"301221","name":"undefined + 3.3%"},{"id":"301222","name":"undefined + 3.7%"},{"id":"301223","name":"undefined + 4.2%"},{"id":"301224","name":"undefined + 4.7%"},{"id":"301231","name":"undefined + 2.7%"},{"id":"301232","name":"undefined + 3.1%"},{"id":"301233","name":"undefined + 3.5%"},{"id":"301234","name":"undefined + 3.9%"},{"id":"301241","name":"undefined + 979.0%"},{"id":"301242","name":"undefined + 1119.0%"},{"id":"301243","name":"undefined + 1259.0%"},{"id":"301244","name":"undefined + 1399.0%"},{"id":"401021","name":"undefined + 167"},{"id":"401022","name":"undefined + 191"},{"id":"401023","name":"undefined + 215"},{"id":"401024","name":"undefined + 239"},{"id":"401031","name":"undefined + 3.3%"},{"id":"401032","name":"undefined + 3.7%"},{"id":"401033","name":"undefined + 4.2%"},{"id":"401034","name":"undefined + 4.7%"},{"id":"401051","name":"undefined + 11"},{"id":"401052","name":"undefined + 12"},{"id":"401053","name":"undefined + 14"},{"id":"401054","name":"undefined + 16"},{"id":"401061","name":"undefined + 3.3%"},{"id":"401062","name":"undefined + 3.7%"},{"id":"401063","name":"undefined + 4.2%"},{"id":"401064","name":"undefined + 4.7%"},{"id":"401081","name":"undefined + 13"},{"id":"401082","name":"undefined + 15"},{"id":"401083","name":"undefined + 17"},{"id":"401084","name":"undefined + 19"},{"id":"401091","name":"undefined + 4.1%"},{"id":"401092","name":"undefined + 4.7%"},{"id":"401093","name":"undefined + 5.3%"},{"id":"401094","name":"undefined + 5.8%"},{"id":"401201","name":"undefined + 2.2%"},{"id":"401202","name":"undefined + 2.5%"},{"id":"401203","name":"undefined + 2.8%"},{"id":"401204","name":"undefined + 3.1%"},{"id":"401221","name":"undefined + 4.3%"},{"id":"401222","name":"undefined + 5.0%"},{"id":"401223","name":"undefined + 5.6%"},{"id":"401224","name":"undefined + 6.2%"},{"id":"401231","name":"undefined + 3.6%"},{"id":"401232","name":"undefined + 4.1%"},{"id":"401233","name":"undefined + 4.7%"},{"id":"401234","name":"undefined + 5.2%"},{"id":"401241","name":"undefined + 1306.0%"},{"id":"401242","name":"undefined + 1492.0%"},{"id":"401243","name":"undefined + 1679.0%"},{"id":"401244","name":"undefined + 1865.0%"},{"id":"501021","name":"undefined + 209"},{"id":"501022","name":"undefined + 239"},{"id":"501023","name":"undefined + 269"},{"id":"501024","name":"undefined + 299"},{"id":"501031","name":"undefined + 4.1%"},{"id":"501032","name":"undefined + 4.7%"},{"id":"501033","name":"undefined + 5.3%"},{"id":"501034","name":"undefined + 5.8%"},{"id":"501051","name":"undefined + 14"},{"id":"501052","name":"undefined + 16"},{"id":"501053","name":"undefined + 18"},{"id":"501054","name":"undefined + 19"},{"id":"501061","name":"undefined + 4.1%"},{"id":"501062","name":"undefined + 4.7%"},{"id":"501063","name":"undefined + 5.3%"},{"id":"501064","name":"undefined + 5.8%"},{"id":"501081","name":"undefined + 16"},{"id":"501082","name":"undefined + 19"},{"id":"501083","name":"undefined + 21"},{"id":"501084","name":"undefined + 23"},{"id":"501091","name":"undefined + 5.1%"},{"id":"501092","name":"undefined + 5.8%"},{"id":"501093","name":"undefined + 6.6%"},{"id":"501094","name":"undefined + 7.3%"},{"id":"501201","name":"undefined + 2.7%"},{"id":"501202","name":"undefined + 3.1%"},{"id":"501203","name":"undefined + 3.5%"},{"id":"501204","name":"undefined + 3.9%"},{"id":"501221","name":"undefined + 5.4%"},{"id":"501222","name":"undefined + 6.2%"},{"id":"501223","name":"undefined + 7.0%"},{"id":"501224","name":"undefined + 7.8%"},{"id":"501231","name":"undefined + 4.5%"},{"id":"501232","name":"undefined + 5.2%"},{"id":"501233","name":"undefined + 5.8%"},{"id":"501234","name":"undefined + 6.5%"},{"id":"501241","name":"undefined + 1632.0%"},{"id":"501242","name":"undefined + 1865.0%"},{"id":"501243","name":"undefined + 2098.0%"},{"id":"501244","name":"undefined + 2331.0%"},{"id":"941001","name":"undefined + 9.3%"},{"id":"941002","name":"undefined + 9.3%"},{"id":"941003","name":"undefined + 11.7%"},{"id":"941004","name":"undefined + 6.2%"},{"id":"941005","name":"undefined + 10.4%"},{"id":"941006","name":"undefined + 3730.0%"},{"id":"941007","name":"undefined + 12.4%"},{"id":"942001","name":"undefined + 9.3%"},{"id":"942002","name":"undefined + 9.3%"},{"id":"942003","name":"undefined + 11.7%"},{"id":"942004","name":"undefined + 6.2%"},{"id":"942005","name":"undefined + 10.4%"},{"id":"942006","name":"undefined + 3730.0%"},{"id":"942007","name":"undefined + 12.4%"},{"id":"943001","name":"undefined + 9.3%"},{"id":"943002","name":"undefined + 9.3%"},{"id":"943003","name":"undefined + 11.7%"},{"id":"943004","name":"undefined + 6.2%"},{"id":"943005","name":"undefined + 10.4%"},{"id":"943006","name":"undefined + 3730.0%"},{"id":"943007","name":"undefined + 12.4%"},{"id":"946001","name":"undefined + 9.3%"},{"id":"946002","name":"undefined + 9.3%"},{"id":"946003","name":"undefined + 11.7%"},{"id":"946004","name":"undefined + 6.2%"},{"id":"946005","name":"undefined + 10.4%"},{"id":"946006","name":"undefined + 3730.0%"},{"id":"946007","name":"undefined + 12.4%"},{"id":"951001","name":"undefined + 14.6%"},{"id":"951002","name":"undefined + 14.6%"},{"id":"951003","name":"undefined + 18.2%"},{"id":"951004","name":"undefined + 9.7%"},{"id":"951005","name":"undefined + 16.2%"},{"id":"951006","name":"undefined + 5828.0%"},{"id":"951007","name":"undefined + 19.4%"},{"id":"952001","name":"undefined + 14.6%"},{"id":"952002","name":"undefined + 14.6%"},{"id":"952003","name":"undefined + 18.2%"},{"id":"952004","name":"undefined + 9.7%"},{"id":"952005","name":"undefined + 16.2%"},{"id":"952006","name":"undefined + 5828.0%"},{"id":"952007","name":"undefined + 19.4%"},{"id":"953001","name":"undefined + 14.6%"},{"id":"953002","name":"undefined + 14.6%"},{"id":"953003","name":"undefined + 18.2%"},{"id":"953004","name":"undefined + 9.7%"},{"id":"953005","name":"undefined + 16.2%"},{"id":"953006","name":"undefined + 5828.0%"},{"id":"953007","name":"undefined + 19.4%"},{"id":"956001","name":"undefined + 14.6%"},{"id":"956002","name":"undefined + 14.6%"},{"id":"956003","name":"undefined + 18.2%"},{"id":"956004","name":"undefined + 9.7%"},{"id":"956005","name":"undefined + 16.2%"},{"id":"956006","name":"undefined + 5828.0%"},{"id":"956007","name":"undefined + 19.4%"},{"id":"961001","name":"undefined + 14.6%"},{"id":"961002","name":"undefined + 14.6%"},{"id":"961003","name":"undefined + 18.2%"},{"id":"961004","name":"undefined + 9.7%"},{"id":"961005","name":"undefined + 16.2%"},{"id":"961006","name":"undefined + 5828.0%"},{"id":"961007","name":"undefined + 19.4%"},{"id":"961008","name":"undefined + 747"},{"id":"961009","name":"undefined + 49"},{"id":"961010","name":"undefined + 58"},{"id":"962001","name":"undefined + 14.6%"},{"id":"962002","name":"undefined + 14.6%"},{"id":"962003","name":"undefined + 18.2%"},{"id":"962004","name":"undefined + 9.7%"},{"id":"962005","name":"undefined + 16.2%"},{"id":"962006","name":"undefined + 5828.0%"},{"id":"962007","name":"undefined + 19.4%"},{"id":"962008","name":"undefined + 747"},{"id":"962009","name":"undefined + 49"},{"id":"962010","name":"undefined + 58"},{"id":"963001","name":"undefined + 14.6%"},{"id":"963002","name":"undefined + 14.6%"},{"id":"963003","name":"undefined + 18.2%"},{"id":"963004","name":"undefined + 9.7%"},{"id":"963005","name":"undefined + 16.2%"},{"id":"963006","name":"undefined + 5828.0%"},{"id":"963007","name":"undefined + 19.4%"},{"id":"963008","name":"undefined + 747"},{"id":"963009","name":"undefined + 49"},{"id":"963010","name":"undefined + 58"},{"id":"964001","name":"undefined + 14.6%"},{"id":"964002","name":"undefined + 14.6%"},{"id":"964003","name":"undefined + 18.2%"},{"id":"964004","name":"undefined + 9.7%"},{"id":"964005","name":"undefined + 16.2%"},{"id":"964006","name":"undefined + 5828.0%"},{"id":"964007","name":"undefined + 19.4%"},{"id":"964008","name":"undefined + 747"},{"id":"964009","name":"undefined + 49"},{"id":"964010","name":"undefined + 58"},{"id":"965001","name":"undefined + 14.6%"},{"id":"965002","name":"undefined + 14.6%"},{"id":"965003","name":"undefined + 18.2%"},{"id":"965004","name":"undefined + 9.7%"},{"id":"965005","name":"undefined + 16.2%"},{"id":"965006","name":"undefined + 5828.0%"},{"id":"965007","name":"undefined + 19.4%"},{"id":"965008","name":"undefined + 747"},{"id":"965009","name":"undefined + 49"},{"id":"965010","name":"undefined + 58"},{"id":"966001","name":"undefined + 30000.0%"},{"id":"967001","name":"undefined + 100.0%"},{"id":"968001","name":"undefined + -30000.0%"},{"id":"969001","name":"undefined + -500"},{"id":"970001","name":"undefined + 80.0%"},{"id":"971001","name":"undefined + 80.0%"},{"id":"972001","name":"undefined + 80.0%"},{"id":"973001","name":"undefined + 80.0%"},{"id":"974001","name":"undefined + 80.0%"},{"id":"975001","name":"undefined + 80.0%"},{"id":"976001","name":"undefined + 80.0%"},{"id":"977001","name":"undefined + 80.0%"},{"id":"978001","name":"undefined + 80.0%"},{"id":"979001","name":"undefined + 80.0%"},{"id":"980001","name":"undefined + 80.0%"},{"id":"981001","name":"undefined + 80.0%"},{"id":"982001","name":"undefined + 80.0%"},{"id":"983001","name":"undefined + 80.0%"},{"id":"984001","name":"undefined + 80.0%"},{"id":"985001","name":"undefined + 80.0%"},{"id":"986001","name":"undefined + 80.0%"},{"id":"987001","name":"undefined + 80.0%"},{"id":"988001","name":"undefined + 30.0%"},{"id":"989001","name":"undefined + 50.0%"},{"id":"990001","name":"undefined + 1"},{"id":"991001","name":"undefined + 80.0%"},{"id":"992001","name":"undefined + 80.0%"},{"id":"993001","name":"undefined + 80.0%"},{"id":"994001","name":"undefined + 80.0%"},{"id":"995001","name":"undefined + 14.6%"},{"id":"995002","name":"undefined + 14.6%"},{"id":"995003","name":"undefined + 18.2%"},{"id":"995004","name":"undefined + 9.7%"},{"id":"995005","name":"undefined + 16.2%"},{"id":"995006","name":"undefined + 5828.0%"},{"id":"995007","name":"undefined + 19.4%"},{"id":"996001","name":"undefined + 9.3%"},{"id":"996002","name":"undefined + 9.3%"},{"id":"996003","name":"undefined + 11.7%"},{"id":"996004","name":"undefined + 6.2%"},{"id":"996005","name":"undefined + 10.4%"},{"id":"996006","name":"undefined + 3730.0%"},{"id":"996007","name":"undefined + 12.4%"},{"id":"996008","name":"undefined + 478"},{"id":"996009","name":"undefined + 31"},{"id":"996010","name":"undefined + 37"},{"id":"997001","name":"undefined + 9.3%"},{"id":"997002","name":"undefined + 9.3%"},{"id":"997003","name":"undefined + 11.7%"},{"id":"997004","name":"undefined + 6.2%"},{"id":"997005","name":"undefined + 10.4%"},{"id":"997006","name":"undefined + 3730.0%"},{"id":"997007","name":"undefined + 12.4%"},{"id":"998001","name":"undefined + 14.6%"},{"id":"998002","name":"undefined + 14.6%"},{"id":"998003","name":"undefined + 18.2%"},{"id":"998004","name":"undefined + 9.7%"},{"id":"998005","name":"undefined + 16.2%"},{"id":"998006","name":"undefined + 5828.0%"},{"id":"998007","name":"undefined + 19.4%"},{"id":"999001","name":"undefined + 350.0%"},{"id":"999002","name":"undefined + 100.0%"},{"id":"999003","name":"undefined + 233333"},{"id":"999004","name":"undefined + 233333"}]}]